alluka/__init__.py
alluka/_client.py
alluka/_context.py
alluka/_errors.py
alluka/_self_injecting.py
alluka/_types.py
alluka/_visitor.py
alluka/abc.py
alluka/local.py
alluka/py.typed
alluka-0.4.0.dist-info/LICENSE
alluka-0.4.0.dist-info/WHEEL
alluka-0.4.0.dist-info/METADATA
alluka-0.4.0.dist-info/RECORD
