Metadata-Version: 2.3
Name: alluka
Version: 0.4.0
Summary: A type based dependency injection framework for Python 3.9+.
Keywords: DI,injection,dependency injection
Author-email: Faster Speeding <lucina@lmbyrne.dev>
Requires-Python: >=3.11.0,<3.15
Classifier: Development Status :: 4 - Beta
Classifier: Framework :: AnyIO
Classifier: Framework :: AsyncIO
Classifier: Framework :: Trio
Classifier: License :: OSI Approved :: BSD License
Classifier: Intended Audience :: Developers
Classifier: Natural Language :: English
Classifier: Operating System :: OS Independent
Classifier: Programming Language :: Python :: 3.11
Classifier: Programming Language :: Python :: 3.12
Classifier: Programming Language :: Python :: 3.13
Classifier: Programming Language :: Python :: Implementation :: CPython
Classifier: Topic :: Software Development :: Libraries
Classifier: Topic :: Software Development :: Libraries :: Python Modules
Classifier: Topic :: Utilities
Classifier: Typing :: Typed
Requires-Dist: typing-extensions>=4.5, <5
Project-URL: Changelog, https://alluka.cursed.solutions/changelog
Project-URL: Documentation, https://alluka.cursed.solutions/
Project-URL: Homepage, https://github.com/FasterSpeeding/Alluka
Project-URL: Repository, https://github.com/FasterSpeeding/Alluka
